opentelemetry/instrumentation/aiobotocore/__init__.py
opentelemetry/instrumentation/aiobotocore/environment_variables.py
opentelemetry/instrumentation/aiobotocore/package.py
opentelemetry/instrumentation/aiobotocore/version.py
opentelemetry/instrumentation/aiobotocore/extensions/__init__.py
opentelemetry/instrumentation/aiobotocore/extensions/_messaging.py
opentelemetry/instrumentation/aiobotocore/extensions/dynamodb.py
opentelemetry/instrumentation/aiobotocore/extensions/lmbd.py
opentelemetry/instrumentation/aiobotocore/extensions/sns.py
opentelemetry/instrumentation/aiobotocore/extensions/sqs.py
opentelemetry/instrumentation/aiobotocore/extensions/types.py
aiobotocore_otel-1.2.0.dist-info/METADATA
aiobotocore_otel-1.2.0.dist-info/WHEEL
aiobotocore_otel-1.2.0.dist-info/entry_points.txt
aiobotocore_otel-1.2.0.dist-info/licenses/LICENSE
aiobotocore_otel-1.2.0.dist-info/RECORD
